.gitignore
CHANGELOG.md
LICENSE
MANIFEST.in
README.md
requirements.txt
setup.cfg
setup.py
.github/CODE_OF_CONDUCT.md
.github/CONTRIBUTING.md
.github/ISSUE_TEMPLATE/bug_report.md
.github/ISSUE_TEMPLATE/feature_request.md
.github/ISSUE_TEMPLATE/question.md
freegenes/__init__.py
freegenes/version.py
freegenes.egg-info/PKG-INFO
freegenes.egg-info/SOURCES.txt
freegenes.egg-info/dependency_links.txt
freegenes.egg-info/entry_points.txt
freegenes.egg-info/not-zip-safe
freegenes.egg-info/requires.txt
freegenes.egg-info/top_level.txt
freegenes/client/__init__.py
freegenes/client/shell.py
freegenes/client/twist.py
freegenes/logger/__init__.py
freegenes/logger/compatibility.py
freegenes/logger/message.py
freegenes/logger/progress.py
freegenes/logger/spinner.py
freegenes/main/__init__.py
freegenes/main/cache.py
freegenes/main/helpers.py
freegenes/main/twist.py
freegenes/tests/__init__.py
freegenes/tests/test_client.py
freegenes/utils/__init__.py
freegenes/utils/convert.py
freegenes/utils/fileio.py
freegenes/utils/terminal.py